cli/main.py
cli/utils/__init__.py
coldshard_cli-0.1.2.dist-info/LICENSE
coldshard_cli-0.1.2.dist-info/METADATA
coldshard_cli-0.1.2.dist-info/WHEEL
coldshard_cli-0.1.2.dist-info/entry_points.txt
coldshard_cli-0.1.2.dist-info/top_level.txt
coldshard_cli-0.1.2.dist-info/RECORD
