Metadata-Version: 2.1
Name: coldshard-cli
Version: 0.1.2
Author: ColdShard LLC
Author-email: TheUntraceable@TheUntraceable.me
License-File: LICENSE
Requires-Dist: Click
Requires-Dist: Requests
Requires-Dist: Inquirer
